{
  "project_info": {
    "project_number": "830603181888",
    "project_id": "something-33869",
    "storage_bucket": "something-33869.appspot.com"
  },
  "client": [
    {
      "client_info": {
        "mobilesdk_app_id": "1:830603181888:android:e50708f86d9fbbd9b444a5",
        "android_client_info": {
          "package_name": "com.p1ritos.something"
        }
      },
      "oauth_client": [],
      "api_key": [
        {
          "current_key": "AIzaSyDRvF1ZiN_kFbL8rzhqlcDNt1lm-XlsGQ4"
        }
      ],
      "services": {
        "appinvite_service": {
          "other_platform_oauth_client": []
        }
      }
    }
  ],
  "configuration_version": "1"
}